Datapath/alu.v
module alu(
    input [31:0]a, // Input A.
    input [31:0]b, // Input B.
    input [1:0]sel,  // Select Input for operations to be performed.
    output reg [31:0]result,

    output wire zero,  // <-- Flags 
    output reg negative,
    output reg overflow,
    output reg carry
);

parameter A=0, B=1, c=2, d=3;
// (a) is for (and) operation.
// (b) is for (or) operation.
// (c) is for (addition) operation.
// (d) is for (Subtraction) operation.
initial begin 
    negative = 1'b0;
    overflow = 1'b0;
    carry = 1'b0;
end 

always @(*) begin 
    case(sel)
    A: begin 
        result = a&b;  // Bitwise and operation.
        carry = 1'b0;
        overflow = 1'b0;
    end

    B: begin 
        result = a|b;  // Bitwise or operation.
        carry = 1'b0;
        overflow = 1'b0;
    end

    c: begin 
        {carry,result} = a+b;
        overflow = carry;
    end

    d: begin 
        {carry,result} = a-b;   // Imprve the subtraction based on the signed and unsigned representation.
        overflow = carry;
    end 

    default: begin 
        result = 32'b0;
        carry = 1'b0;
        overflow = 1'b0;
    end
    endcase

end

assign zero = (result==32'b0)?1'b1:1'b0;


endmodule

ALU/testbench1.v
`timescale 1ns/1ns
module testbench;
reg [31:0]a,b;
reg [1:0]sel;
wire [31:0]result;
wire zero, negative, carry, overflow;
alu alu1(a,b,sel,result,zero,negative,overflow,carry);

initial begin
    $dumpfile("test.vcd");
    $dumpvars(0,testbench);
    $monitor("time=%0t a=%d b=%d sel=%d result=%d", $time, a, b, sel, result);
end

initial begin 
// Initialize
    a = 32'd0;
    b = 32'd0;
    sel = 4'd0;

    // Test ADD
    #10 a = 32'd10; b = 32'd5;  sel = 4'd0;

    // Test SUB
    #10 a = 32'd20; b = 32'd8;  sel = 4'd1;

    // Test AND
    #10 a = 32'hF0F0F0F0; b = 32'h0F0F0F0F; sel = 4'd2;

    // Test OR
    #10 a = 32'hAAAA5555; b = 32'h5555AAAA; sel = 4'd3;

    // Test XOR
    #10 a = 32'h12345678; b = 32'h87654321; sel = 4'd4;

    // Test SLT
    #10 a = 32'd5; b = 32'd10; sel = 4'd5;

    // Test Shift Left
    #10 a = 32'h00000001; b = 32'd4; sel = 4'd6;

    // Test Shift Right
    #10 a = 32'h00000010; b = 32'd2; sel = 4'd7;

    #10 $finish;

end
endmodule

ALU/test.vcd
$date
	Sat Mar  7 18:56:31 2026
$end
$version
	Icarus Verilog
$end
$timescale
	1ns
$end
$scope module testbench $end
$var wire 1 ! zero $end
$var wire 32 " result [31:0] $end
$var wire 1 # overflow $end
$var wire 1 $ negative $end
$var wire 1 % carry $end
$var reg 32 & a [31:0] $end
$var reg 32 ' b [31:0] $end
$var reg 2 ( sel [1:0] $end
$scope module alu1 $end
$var wire 32 ) a [31:0] $end
$var wire 32 * b [31:0] $end
$var wire 2 + sel [1:0] $end
$var wire 1 ! zero $end
$var parameter 32 , A $end
$var parameter 32 - B $end
$var parameter 32 . c $end
$var parameter 32 / d $end
$var reg 1 % carry $end
$var reg 1 $ negative $end
$var reg 1 # overflow $end
$var reg 32 0 result [31:0] $end
$upscope $end
$upscope $end
$enddefinitions $end
$comment Show the parameter values. $end
$dumpall
b11 /
b10 .
b1 -
b0 ,
$end
#0
$dumpvars
b0 0
b0 +
b0 *
b0 )
b0 (
b0 '
b0 &
0%
0$
0#
b0 "
1!
$end
#10
b101 '
b101 *
b1010 &
b1010 )
#20
0!
b11100 "
b11100 0
b1 (
b1 +
b1000 '
b1000 *
b10100 &
b10100 )
#30
b11111111111111111111111111111111 "
b11111111111111111111111111111111 0
b10 (
b10 +
b1111000011110000111100001111 '
b1111000011110000111100001111 *
b11110000111100001111000011110000 &
b11110000111100001111000011110000 )
#40
b1010101010101001010101010101011 "
b1010101010101001010101010101011 0
b11 (
b11 +
b1010101010101011010101010101010 '
b1010101010101011010101010101010 *
b10101010101010100101010101010101 &
b10101010101010100101010101010101 )
#50
b10001001000100001000100000 "
b10001001000100001000100000 0
b0 (
b0 +
b10000111011001010100001100100001 '
b10000111011001010100001100100001 *
b10010001101000101011001111000 &
b10010001101000101011001111000 )
#60
b1111 "
b1111 0
b1 (
b1 +
b1010 '
b1010 *
b101 &
b101 )
#70
b101 "
b101 0
b10 (
b10 +
b100 '
b100 *
b1 &
b1 )
#80
b1110 "
b1110 0
b11 (
b11 +
b10 '
b10 *
b10000 &
b10000 )
